README.md
setup.py
attentionmech/__init__.py
attentionmech/attention.py
attentionmech.egg-info/PKG-INFO
attentionmech.egg-info/SOURCES.txt
attentionmech.egg-info/dependency_links.txt
attentionmech.egg-info/requires.txt
attentionmech.egg-info/top_level.txt