Metadata-Version: 2.1
Name: attentionmech
Version: 0.0.1
Summary: attentionmech is an independent Open Source, Natural Language Processing python library which implements a self attention mechanisam
Home-page: https://github.com/sayanmondal2098/attentionmech
Author: Sayan Mondal(ph3n1x)
Author-email: sayanmondal2098@gmail.com
License: MIT
Download-URL: https://github.com/sayanmondal2098/attentionmech
Keywords: NLP,Natural Language Processing,Tokenization,Text Summarization,Text Processing,Sentiment Analysis
Platform: UNKNOWN
Classifier: Development Status :: 5 - Production/Stable
Classifier: Intended Audience :: Developers
Classifier: Topic :: Software Development :: Build Tools
Classifier: License :: OSI Approved :: MIT License
Classifier: Operating System :: OS Independent
Classifier: Programming Language :: Python :: 3
Classifier: Programming Language :: Python :: 3.4
Classifier: Programming Language :: Python :: 3.5
Classifier: Programming Language :: Python :: 3.6
Classifier: Programming Language :: Python :: 3.7
